dbt/adapters/iris/__init__.py
dbt/adapters/iris/__version__.py
dbt/adapters/iris/column.py
dbt/adapters/iris/connections.py
dbt/adapters/iris/impl.py
dbt/adapters/iris/relation.py
dbt/include/iris/__init__.py
dbt/include/iris/dbt_project.yml
dbt/include/iris/profile_iris.yml
dbt/include/iris/macros/adapters.sql
dbt/include/iris/macros/apply_grants.sql
dbt/include/iris/macros/catalog.sql
dbt/include/iris/macros/columns.sql
dbt/include/iris/macros/datatypes.sql
dbt/include/iris/macros/helpers.sql
dbt/include/iris/macros/adapters/columns.sql
dbt/include/iris/macros/adapters/relation.sql
dbt/include/iris/macros/materializations/table.sql
dbt/include/iris/macros/materializations/view.sql
dbt/include/iris/macros/materializations/incremental/incremental.sql
dbt/include/iris/macros/materializations/incremental/strategies.sql
dbt/include/iris/macros/materializations/seeds/helpers.sql
dbt/include/iris/macros/materializations/snapshots/helpers.sql
dbt/include/iris/macros/materializations/snapshots/snapshot.sql
dbt/include/iris/macros/materializations/snapshots/snapshot_merge.sql
dbt/include/iris/macros/materializations/snapshots/strategies.sql
dbt/include/iris/macros/materializations/test/test.sql
dbt/include/iris/macros/models/merge.sql
dbt/include/iris/macros/relations/table/drop.sql
dbt/include/iris/macros/relations/view/replace.sql
dbt/include/iris/macros/utils/hash.sql
dbt/include/iris/macros/utils/split_part.sql
intersystems_iris/_BufferReader.py
intersystems_iris/_BufferWriter.py
intersystems_iris/_ConnectionInformation.py
intersystems_iris/_ConnectionParameters.py
intersystems_iris/_Constant.py
intersystems_iris/_DBList.py
intersystems_iris/_Device.py
intersystems_iris/_GatewayContext.py
intersystems_iris/_GatewayException.py
intersystems_iris/_GatewayUtility.py
intersystems_iris/_IRIS.py
intersystems_iris/_IRISConnection.py
intersystems_iris/_IRISEmbedded.py
intersystems_iris/_IRISGlobalNode.py
intersystems_iris/_IRISGlobalNodeView.py
dbt_iris-1.9.2.dist-info/LICENSE
dbt_iris-1.9.2.dist-info/METADATA
dbt_iris-1.9.2.dist-info/WHEEL
dbt_iris-1.9.2.dist-info/top_level.txt
dbt_iris-1.9.2.dist-info/RECORD
