Metadata-Version: 2.2
Name: dbt-iris
Version: 1.9.2
Summary: The InterSystems IRIS adapter plugin for dbt
Home-page: https://github.com/caretdev/dbt-iris
Author: CaretDev
Author-email: info@caretdev.com
License: MIT
Classifier: Development Status :: 5 - Production/Stable
Classifier: License :: OSI Approved :: MIT License
Classifier: Operating System :: OS Independent
Classifier: Programming Language :: Python :: 3.8
Classifier: Programming Language :: Python :: 3.9
Classifier: Programming Language :: Python :: 3.10
Classifier: Programming Language :: Python :: 3.11
Requires-Python: >3.7
License-File: LICENSE
Requires-Dist: dbt-adapters<2.0,>=1.1.1
Requires-Dist: dbt-core>=1.8.0
Requires-Dist: dbt-common<2.0,>=1.0.4
Dynamic: author
Dynamic: author-email
Dynamic: classifier
Dynamic: description
Dynamic: home-page
Dynamic: license
Dynamic: requires-dist
Dynamic: requires-python
Dynamic: summary
